tests/__init__.py
tests/test_location_util.py
tests/test_vwsfriend.py
vwsfriend/__init__.py
vwsfriend/__main__.py
vwsfriend/__version.py
vwsfriend/agent_connector.py
vwsfriend/privacy.py
vwsfriend/vwsfriend_base.py
vwsfriend/agents/__init__.py
vwsfriend/agents/battery_agent.py
vwsfriend/agents/charge_agent.py
vwsfriend/agents/climatization_agent.py
vwsfriend/agents/maintenance_agent.py
vwsfriend/agents/range_agent.py
vwsfriend/agents/refuel_agent.py
vwsfriend/agents/state_agent.py
vwsfriend/agents/trip_agent.py
vwsfriend/agents/warning_light_agent.py
vwsfriend/agents/weconnect_error_agent.py
vwsfriend/agents/abrp/__init__.py
vwsfriend/agents/abrp/abrp_agent.py
vwsfriend/homekit/__init__.py
vwsfriend/homekit/battery.py
vwsfriend/homekit/battery_temperature.py
vwsfriend/homekit/bridge.py
vwsfriend/homekit/charging.py
vwsfriend/homekit/climatization.py
vwsfriend/homekit/custom_characteristics.py
vwsfriend/homekit/dummy_accessory.py
vwsfriend/homekit/flashing.py
vwsfriend/homekit/genericAccessory.py
vwsfriend/homekit/locking_system.py
vwsfriend/homekit/plug.py
vwsfriend/model/__init__.py
vwsfriend/model/base.py
vwsfriend/model/battery.py
vwsfriend/model/battery_temperature.py
vwsfriend/model/charge.py
vwsfriend/model/charger.py
vwsfriend/model/charging_session.py
vwsfriend/model/climatization.py
vwsfriend/model/datetime_decorator.py
vwsfriend/model/geofence.py
vwsfriend/model/journey.py
vwsfriend/model/location.py
vwsfriend/model/maintenance.py
vwsfriend/model/migrations.py
vwsfriend/model/online.py
vwsfriend/model/range.py
vwsfriend/model/refuel_session.py
vwsfriend/model/settings.py
vwsfriend/model/tag.py
vwsfriend/model/trip.py
vwsfriend/model/vehicle.py
vwsfriend/model/vehicle_settings.py
vwsfriend/model/warning_light.py
vwsfriend/model/weconnect_error.py
vwsfriend/model/weconnect_responsetime.py
vwsfriend/model/vwsfriend-schema/__init__.py
vwsfriend/model/vwsfriend-schema/env.py
vwsfriend-0.24.7.dist-info/METADATA
vwsfriend-0.24.7.dist-info/WHEEL
vwsfriend-0.24.7.dist-info/entry_points.txt
vwsfriend-0.24.7.dist-info/top_level.txt
vwsfriend-0.24.7.dist-info/RECORD
