Metadata-Version: 2.1
Name: vwsfriend
Version: 0.24.7
Home-page: https://github.com/tillsteinbach/VWsFriend
Author: Till Steinbach
License: MIT
Project-URL: Funding, https://github.com/sponsors/VWsFriend
Project-URL: Source, https://github.com/tillsteinbach/VWsFriend
Project-URL: Bug Tracker, https://github.com/tillsteinbach/VWsFriend/issues
Keywords: weconnect,we connect,carnet,car net,volkswagen,vw,telemetry,smarthome
Classifier: Development Status :: 3 - Alpha
Classifier: Environment :: Console
Classifier: License :: OSI Approved :: MIT License
Classifier: Intended Audience :: End Users/Desktop
Classifier: Intended Audience :: System Administrators
Classifier: Programming Language :: Python :: 3.8
Classifier: Programming Language :: Python :: 3.9
Classifier: Programming Language :: Python :: 3.10
Classifier: Programming Language :: Python :: 3.11
Classifier: Programming Language :: Python :: 3.12
Classifier: Topic :: Utilities
Classifier: Topic :: System :: Monitoring
Classifier: Topic :: Home Automation
Requires-Python: >=3.8
Requires-Dist: weconnect[images]~=0.60.5
Requires-Dist: HAP-python[qrcode]~=4.9.1
Requires-Dist: pypng~=0.20220715.0
Requires-Dist: sqlalchemy~=2.0.34
Requires-Dist: psycopg2-binary~=2.9.9
Requires-Dist: requests~=2.32.3
Requires-Dist: Werkzeug~=3.0.4
Requires-Dist: Flask~=3.0.3
Requires-Dist: flask-login~=0.6.3
Requires-Dist: flask-caching~=2.3.0
Requires-Dist: WTForms~=3.1.2
Requires-Dist: flask-wtf~=1.2.1
Requires-Dist: flask-sqlalchemy~=3.1.1
Requires-Dist: alembic~=1.13.2
Requires-Dist: haversine~=2.8.1
Provides-Extra: mqtt
Requires-Dist: weconnect-mqtt~=0.49.2; extra == "mqtt"
